LICENSE
MANIFEST.in
build.vel
setup.py
bin/lamson
doc/requires.txt
doc/lamsonproject.org/Session.vim
doc/lamsonproject.org/build.vel
doc/lamsonproject.org/config.py
doc/lamsonproject.org/template.html
doc/lamsonproject.org/webgen.py
doc/lamsonproject.org/input/about.txt
doc/lamsonproject.org/input/contact.txt
doc/lamsonproject.org/input/download.txt
doc/lamsonproject.org/input/home_template.html
doc/lamsonproject.org/input/index.txt
doc/lamsonproject.org/input/blog/2009-05-16.txt
doc/lamsonproject.org/input/blog/2009-05-18.txt
doc/lamsonproject.org/input/blog/2009-05-19.txt
doc/lamsonproject.org/input/blog/2009-05-20.txt
doc/lamsonproject.org/input/blog/2009-05-24.txt
doc/lamsonproject.org/input/blog/2009-05-28.txt
doc/lamsonproject.org/input/blog/2009-05-31.txt
doc/lamsonproject.org/input/blog/2009-06-01.txt
doc/lamsonproject.org/input/blog/2009-06-03-2.txt
doc/lamsonproject.org/input/blog/2009-06-03.txt
doc/lamsonproject.org/input/blog/2009-06-04.txt
doc/lamsonproject.org/input/blog/2009-06-06.txt
doc/lamsonproject.org/input/blog/2009-06-08.txt
doc/lamsonproject.org/input/blog/2009-06-09.txt
doc/lamsonproject.org/input/blog/2009-06-14.txt
doc/lamsonproject.org/input/blog/2009-06-20.txt
doc/lamsonproject.org/input/blog/2009-06-22.txt
doc/lamsonproject.org/input/blog/2009-06-26.txt
doc/lamsonproject.org/input/blog/2009-07-03.txt
doc/lamsonproject.org/input/blog/2009-07-07.txt
doc/lamsonproject.org/input/blog/2009-07-09.txt
doc/lamsonproject.org/input/blog/2009-07-14.txt
doc/lamsonproject.org/input/blog/2009-07-19.txt
doc/lamsonproject.org/input/blog/2009-07-20.txt
doc/lamsonproject.org/input/blog/2009-08-03.txt
doc/lamsonproject.org/input/blog/2009-08-22.txt
doc/lamsonproject.org/input/blog/2009-09-07.txt
doc/lamsonproject.org/input/blog/2009-09-26.txt
doc/lamsonproject.org/input/blog/2009-12-12.txt
doc/lamsonproject.org/input/blog/2009-12-20.txt
doc/lamsonproject.org/input/blog/html_email_in_gmail.png
doc/lamsonproject.org/input/blog/index.txt
lamson.egg-info/PKG-INFO
lamson.egg-info/SOURCES.txt
lamson.egg-info/dependency_links.txt
lamson.egg-info/requires.txt
lamson.egg-info/top_level.txt
