Metadata-Version: 1.0
Name: lamson
Version: 1.3.3
Summary: Lamson is a modern Pythonic mail server built like a web application server.
Home-page: http://pypi.python.org/pypi/lamson
Author: Zed A. Shaw
Author-email: zedshaw@zedshaw.com
License: UNKNOWN
Download-URL: http://pypi.python.org/pypi/lamson
Platform: UNKNOWN
